ecofootprint/__init__.py
ecofootprint/ecofootprint.py
ecofootprint-0.1.0.dist-info/LICENSE
ecofootprint-0.1.0.dist-info/METADATA
ecofootprint-0.1.0.dist-info/WHEEL
ecofootprint-0.1.0.dist-info/top_level.txt
ecofootprint-0.1.0.dist-info/RECORD
